hud/__init__.py
hud/__main__.py
hud/settings.py
hud/types.py
hud/version.py
hud/agents/__init__.py
hud/agents/base.py
hud/agents/claude.py
hud/agents/grounded_openai.py
hud/agents/langchain.py
hud/agents/lite_llm.py
hud/agents/openai.py
hud/agents/openai_chat_generic.py
hud/agents/misc/__init__.py
hud/agents/misc/integration_test_agent.py
hud/agents/misc/response_agent.py
hud/agents/tests/__init__.py
hud/agents/tests/test_base.py
hud/agents/tests/test_claude.py
hud/agents/tests/test_client.py
hud/agents/tests/test_grounded_openai_agent.py
hud/agents/tests/test_openai.py
hud/cli/__init__.py
hud/cli/__main__.py
hud/cli/analyze.py
hud/cli/build.py
hud/cli/clone.py
hud/cli/debug.py
hud/cli/dev.py
hud/cli/eval.py
hud/cli/get.py
hud/cli/init.py
hud/cli/list_func.py
hud/cli/pull.py
hud/cli/push.py
hud/cli/remove.py
hud/cli/flows/__init__.py
hud/cli/flows/tasks.py
hud/cli/rl/__init__.py
hud/cli/rl/celebrate.py
hud/cli/rl/config.py
hud/cli/rl/display.py
hud/cli/rl/gpu.py
hud/cli/rl/gpu_utils.py
hud/cli/rl/local_runner.py
hud/cli/rl/presets.py
hud/cli/rl/remote_runner.py
hud/cli/rl/rl_api.py
hud/cli/rl/viewer.py
hud/cli/rl/vllm.py
hud/cli/rl/wait_utils.py
hud/cli/tests/__init__.py
hud/cli/tests/test_analyze.py
hud/cli/tests/test_analyze_metadata.py
hud/cli/tests/test_build.py
hud/cli/tests/test_cli_init.py
hud/cli/tests/test_cli_main.py
hud/cli/tests/test_clone.py
hud/cli/tests/test_cursor.py
hud/cli/tests/test_debug.py
hud/cli/tests/test_eval.py
hud/cli/tests/test_list_func.py
hud/cli/tests/test_main_module.py
hud/cli/tests/test_mcp_server.py
hud/cli/tests/test_pull.py
hud/cli/tests/test_push.py
hud/cli/tests/test_registry.py
hud/cli/tests/test_utils.py
hud/cli/utils/__init__.py
hud/cli/utils/config.py
hud/cli/utils/cursor.py
hud/cli/utils/docker.py
hud/cli/utils/env_check.py
hud/cli/utils/environment.py
hud/cli/utils/interactive.py
hud/cli/utils/local_runner.py
hud/cli/utils/logging.py
hud/cli/utils/metadata.py
hud/cli/utils/package_runner.py
hud/cli/utils/registry.py
genteki_hdp-0.4.50.1.dist-info/METADATA
genteki_hdp-0.4.50.1.dist-info/WHEEL
genteki_hdp-0.4.50.1.dist-info/entry_points.txt
genteki_hdp-0.4.50.1.dist-info/licenses/LICENSE
genteki_hdp-0.4.50.1.dist-info/RECORD
