Metadata-Version: 2.4
Name: genteki-hdp
Version: 0.4.50.1
Summary: SDK for the HUD platform (Genteki fork with circular import fix).
Project-URL: Homepage, https://github.com/hud-evals/hud-python
Project-URL: Bug Tracker, https://github.com/hud-evals/hud-python/issues
Project-URL: Documentation, https://docs.hud.so
Author-email: HUD SDK <founders@hud.so>
License: MIT License
License-File: LICENSE
Classifier: Development Status :: 4 - Beta
Classifier: Intended Audience :: Developers
Classifier: Programming Language :: Python :: 3
Classifier: Programming Language :: Python :: 3.11
Classifier: Programming Language :: Python :: 3.12
Classifier: Programming Language :: Python :: 3.13
Requires-Python: >=3.11
Requires-Dist: anthropic
Requires-Dist: blessed>=1.20.0
Requires-Dist: datasets>=2.14.0
Requires-Dist: httpx<1,>=0.23.0
Requires-Dist: hud-fastmcp-python-sdk>=0.1.2
Requires-Dist: hud-mcp-python-sdk>=3.13.2
Requires-Dist: hud-mcp-use-python-sdk==2.3.20
Requires-Dist: numpy>=1.24.0
Requires-Dist: openai
Requires-Dist: opentelemetry-api>=1.34.1
Requires-Dist: opentelemetry-exporter-otlp-proto-http>=1.34.1
Requires-Dist: opentelemetry-instrumentation-mcp==0.47.0
Requires-Dist: opentelemetry-sdk>=1.34.1
Requires-Dist: pathspec>=0.12.1
Requires-Dist: pillow>=11.1.0
Requires-Dist: prompt-toolkit==3.0.51
Requires-Dist: pydantic-settings<3,>=2.2
Requires-Dist: pydantic<3,>=2.6
Requires-Dist: questionary==2.1.0
Requires-Dist: rich>=13.0.0
Requires-Dist: toml>=0.10.2
Requires-Dist: typer>=0.9.0
Requires-Dist: watchfiles>=0.21.0
Requires-Dist: wrapt>=1.14.0
Provides-Extra: agent
Requires-Dist: hud-python[dev]; extra == 'agent'
Provides-Extra: agents
Requires-Dist: hud-python[agent]; extra == 'agents'
Provides-Extra: dev
Requires-Dist: aiodocker>=0.24.0; extra == 'dev'
Requires-Dist: dotenv>=0.9.9; extra == 'dev'
Requires-Dist: inspect-ai>=0.3.80; extra == 'dev'
Requires-Dist: ipykernel; extra == 'dev'
Requires-Dist: ipython<9; extra == 'dev'
Requires-Dist: jupyter-client; extra == 'dev'
Requires-Dist: jupyter-core; extra == 'dev'
Requires-Dist: langchain; extra == 'dev'
Requires-Dist: langchain-anthropic; extra == 'dev'
Requires-Dist: langchain-openai; extra == 'dev'
Requires-Dist: litellm>=1.55.0; extra == 'dev'
Requires-Dist: pillow>=11.1.0; extra == 'dev'
Requires-Dist: playwright; extra == 'dev'
Requires-Dist: pyautogui>=0.9.54; extra == 'dev'
Requires-Dist: pyright==1.1.401; extra == 'dev'
Requires-Dist: pytest-asyncio; extra == 'dev'
Requires-Dist: pytest-cov; extra == 'dev'
Requires-Dist: pytest-mock; extra == 'dev'
Requires-Dist: pytest<9,>=8.1.1; extra == 'dev'
Requires-Dist: ruff>=0.11.8; extra == 'dev'
Requires-Dist: setuptools; extra == 'dev'
Requires-Dist: textdistance<5,>=4.5.0; extra == 'dev'
Provides-Extra: rl
Requires-Dist: bitsandbytes>=0.41.0; (sys_platform == 'linux') and extra == 'rl'
Requires-Dist: liger-kernel>=0.5.0; (sys_platform == 'linux') and extra == 'rl'
Requires-Dist: peft>=0.17.1; extra == 'rl'
Requires-Dist: vllm==0.10.1.1; extra == 'rl'
